scisonify/__init__.py
scisonify/pandas.py
scisonify/xarray.py
scisonify/core/__init__.py
scisonify/core/envelope.py
scisonify/core/sonify.py
scisonify/core/soundmaps.py
scisonify/core/waveforms.py
scisonify/tests/test_soundmaps.py
scisonify-1.0.0.dist-info/LICENSE
scisonify-1.0.0.dist-info/METADATA
scisonify-1.0.0.dist-info/WHEEL
scisonify-1.0.0.dist-info/top_level.txt
scisonify-1.0.0.dist-info/RECORD
