Metadata-Version: 2.1
Name: scisonify
Version: 1.0.0
Summary: Turn Scientific Data into Sounds & Music
Author-email: Philip Chmielowiec <philipc@ucar.edu>
Classifier: Operating System :: OS Independent
Classifier: Intended Audience :: Science/Research
Classifier: Programming Language :: Python
Classifier: Programming Language :: Python :: 3
Classifier: Programming Language :: Python :: 3.9
Classifier: Programming Language :: Python :: 3.10
Classifier: Programming Language :: Python :: 3.11
Classifier: Topic :: Scientific/Engineering
Requires-Python: >=3.9
License-File: LICENSE
Requires-Dist: scipy
Requires-Dist: librosa
Requires-Dist: ipython
